{
    "version": "4.2.0-2",
    "description": "A command-line utility that pipes video streams from various services into a video player.",
    "homepage": "https://streamlink.github.io/",
    "license": "BSD-2-Clause",
    "notes": "Streamlink settings can be changed in '%APPDATA%\\streamlink\\config'",
    "suggest": {
        "FFmpeg": [
            "ffmpeg",
            "ffmpeg-nightly"
        ],
        "MPC HC Player": "extras/mpc-hc-fork",
        "VLC Player": "extras/vlc",
        "MPV Player": [
            "extras/mpv",
            "extras/mpv-git"
        ],
        "Streamlink Twitch GUI": "extras/streamlink-twitch-gui"
    },
    "architecture": {
        "64bit": {
            "url": "https://github.com/streamlink/windows-installer/releases/download/4.2.0-2/streamlink-4.2.0-2-py310-x86_64.exe#/dl.7z",
            "hash": "ae7f1cb1d686859280cab218f84a7930256544106247b0beebf7fd1969413f9a"
        },
        "32bit": {
            "url": "https://github.com/streamlink/windows-installer/releases/download/4.2.0-2/streamlink-4.2.0-2-py310-x86.exe#/dl.7z",
            "hash": "53c7f0fde6d1991278a0900889b4adb60f13fcdb8f02d9af025f7badd330e759"
        }
    },
    "pre_install": [
        "if (!(Test-Path \"$env:APPDATA\\streamlink\\config\")) {",
        "    info 'Copying default ''config'' to ''%APPDATA%\\streamlink\\config'''",
        "    ensure \"$env:APPDATA\\streamlink\" | Out-Null",
        "    Copy-Item \"$dir\\`$APPDATA\\streamlink\\config\" \"$env:APPDATA\\streamlink\\config\"",
        "}",
        "Remove-Item \"$dir\\`$*\", \"$dir\\ffmpeg\", \"$dir\\uninstall.exe\" -Recurse"
    ],
    "uninstaller": {
        "script": "if ($purge) { Remove-Item \"$env:APPDATA\\streamlink\" -Recurse}"
    },
    "bin": [
        "bin\\streamlink.exe",
        "bin\\streamlinkw.exe"
    ],
    "checkver": {
        "url": "https://api.github.com/repositories/472790314/releases/latest",
        "jsonpath": "$.tag_name"
    },
    "autoupdate": {
        "architecture": {
            "64bit": {
                "url": "https://github.com/streamlink/windows-installer/releases/download/$version/streamlink-$version-py310-x86_64.exe#/dl.7z"
            },
            "32bit": {
                "url": "https://github.com/streamlink/windows-installer/releases/download/$version/streamlink-$version-py310-x86.exe#/dl.7z"
            }
        }
    }
}
