{
    "version": "1.0.0-pre.2",
    "description": "Terminal-based typing test.",
    "homepage": "https://github.com/max-niederman/ttyper",
    "license": "MIT",
    "architecture": {
        "64bit": {
            "url": "https://github.com/max-niederman/ttyper/releases/download/v1.0.0-pre.2/ttyper-x86_64-pc-windows-msvc.zip",
            "hash": "4eed0f0868ef20858f7c12b67db648523f9fa6dae09f8def2e674d928c2fbe08"
        },
        "32bit": {
            "url": "https://github.com/max-niederman/ttyper/releases/download/v1.0.0-pre.2/ttyper-i686-pc-windows-msvc.zip",
            "hash": "d5ba431cfc0c6e3febf290a882c3ce974d996cfc3714e4439f5b0540919b41c1"
        }
    },
    "bin": "ttyper.exe",
    "checkver": {
        "url": "https://api.github.com/repos/max-niederman/ttyper/releases",
        "jsonpath": "$.[0].tag_name",
        "regex": "v([\\w.-]+)"
    },
    "autoupdate": {
        "architecture": {
            "64bit": {
                "url": "https://github.com/max-niederman/ttyper/releases/download/v$version/ttyper-x86_64-pc-windows-msvc.zip",
                "hash": {
                    "url": "$url.sha256"
                }
            },
            "32bit": {
                "url": "https://github.com/max-niederman/ttyper/releases/download/v$version/ttyper-i686-pc-windows-msvc.zip",
                "hash": {
                    "url": "$url.sha256"
                }
            }
        }
    }
}
